ansys/additive/core/__init__.py
ansys/additive/core/additive.py
ansys/additive/core/conversions.py
ansys/additive/core/download.py
ansys/additive/core/exceptions.py
ansys/additive/core/geometry_file.py
ansys/additive/core/logger.py
ansys/additive/core/machine.py
ansys/additive/core/material.py
ansys/additive/core/material_tuning.py
ansys/additive/core/microstructure.py
ansys/additive/core/microstructure_3d.py
ansys/additive/core/misc.py
ansys/additive/core/porosity.py
ansys/additive/core/progress_handler.py
ansys/additive/core/simulation.py
ansys/additive/core/simulation_error.py
ansys/additive/core/simulation_requests.py
ansys/additive/core/simulation_task.py
ansys/additive/core/simulation_task_manager.py
ansys/additive/core/single_bead.py
ansys/additive/core/thermal_history.py
ansys/additive/core/examples/__init__.py
ansys/additive/core/examples/downloads.py
ansys/additive/core/parametric_study/__init__.py
ansys/additive/core/parametric_study/constants.py
ansys/additive/core/parametric_study/parametric_study.py
ansys/additive/core/parametric_study/parametric_study_progress_handler.py
ansys/additive/core/parametric_study/parametric_utils.py
ansys/additive/core/server_connection/__init__.py
ansys/additive/core/server_connection/constants.py
ansys/additive/core/server_connection/local_server.py
ansys/additive/core/server_connection/network_utils.py
ansys/additive/core/server_connection/server_connection.py
ansys_additive_core-0.20.1.dist-info/licenses/LICENSE
ansys_additive_core-0.20.1.dist-info/WHEEL
ansys_additive_core-0.20.1.dist-info/METADATA
ansys_additive_core-0.20.1.dist-info/RECORD
