Metadata-Version: 2.4
Name: ansys-additive-core
Version: 0.20.1
Summary: A Python client for the Ansys Additive service
Author-email: "ANSYS, Inc." <pyansys.core@ansys.com>
Maintainer-email: "ANSYS, Inc." <pyansys.core@ansys.com>
Requires-Python: >=3.10,<4
Classifier: Development Status :: 4 - Beta
Classifier: Intended Audience :: Manufacturing
Classifier: Topic :: Scientific/Engineering
Classifier: License :: OSI Approved :: MIT License
Classifier: Operating System :: OS Independent
Classifier: Programming Language :: Python :: 3.10
Classifier: Programming Language :: Python :: 3.11
Classifier: Programming Language :: Python :: 3.12
Classifier: Programming Language :: Python :: 3.13
License-File: LICENSE
Requires-Dist: ansys-api-additive==5.0.3
Requires-Dist: ansys-platform-instancemanagement>=1.1.1
Requires-Dist: ansys-tools-common>=0.4.0
Requires-Dist: dill>=0.3.7
Requires-Dist: google-api-python-client>=1.7.11
Requires-Dist: googleapis-common-protos>=1.52.0
Requires-Dist: grpcio>=1.35.0
Requires-Dist: grpcio-health-checking>=1.45.0
Requires-Dist: importlib-metadata>=4.0
Requires-Dist: numpy>=1.20.3
Requires-Dist: pandas>=2.2.2
Requires-Dist: platformdirs>=3.8.0
Requires-Dist: protobuf>=3.20.2,<6
Requires-Dist: six>=1.16.0
Requires-Dist: tqdm>=4.45.0
Requires-Dist: pydantic>=2.6.3
Requires-Dist: ipython>=7.0.0
Requires-Dist: ansys-sphinx-theme[autoapi]==1.5.0 ; extra == "doc"
Requires-Dist: enum-tools==0.13.0 ; extra == "doc"
Requires-Dist: joblib==1.5.1 ; extra == "doc"
Requires-Dist: jupyter_sphinx==0.5.3 ; extra == "doc"
Requires-Dist: matplotlib==3.10.3 ; extra == "doc"
Requires-Dist: numpydoc==1.8.0 ; extra == "doc"
Requires-Dist: phantomjs==1.4.1 ; extra == "doc"
Requires-Dist: pypandoc==1.15 ; extra == "doc"
Requires-Dist: pyvista==0.45.2 ; extra == "doc"
Requires-Dist: ipywidgets==8.1.7 ; extra == "doc"
Requires-Dist: trame==3.10.1 ; extra == "doc"
Requires-Dist: trame-vtk==2.8.15 ; extra == "doc"
Requires-Dist: trame-plotly==3.1.0 ; extra == "doc"
Requires-Dist: trame-vuetify==3.0.1 ; extra == "doc"
Requires-Dist: imageio==2.37.0 ; extra == "doc"
Requires-Dist: sphinx==8.2.3 ; extra == "doc"
Requires-Dist: sphinx-autodoc-typehints==3.1.0 ; extra == "doc"
Requires-Dist: sphinx-copybutton==0.5.2 ; extra == "doc"
Requires-Dist: sphinx-design==0.6.1 ; extra == "doc"
Requires-Dist: sphinx-gallery==0.19.0 ; extra == "doc"
Requires-Dist: sphinx-jinja==2.0.2 ; extra == "doc"
Requires-Dist: sphinx-notfound-page==1.1.0 ; extra == "doc"
Requires-Dist: sphinx-toolbox==4.0.0 ; extra == "doc"
Requires-Dist: sphinxemoji==0.3.1 ; extra == "doc"
Requires-Dist: ipython>=7.0.0 ; extra == "doc"
Requires-Dist: ansys-platform-instancemanagement==1.1.2 ; extra == "tests"
Requires-Dist: dill==0.4.0 ; extra == "tests"
Requires-Dist: google-api-python-client==2.164.0 ; extra == "tests"
Requires-Dist: googleapis-common-protos==1.69.1 ; extra == "tests"
Requires-Dist: grpcio==1.70.0 ; extra == "tests"
Requires-Dist: grpcio-health-checking==1.70.0 ; extra == "tests"
Requires-Dist: numpy==2.2.6 ; extra == "tests"
Requires-Dist: pandas==2.2.3 ; extra == "tests"
Requires-Dist: platformdirs==4.3.8 ; extra == "tests"
Requires-Dist: protobuf==5.29.3 ; extra == "tests"
Requires-Dist: six==1.17.0 ; extra == "tests"
Requires-Dist: tqdm==4.67.1 ; extra == "tests"
Requires-Dist: pydantic==2.11.5 ; extra == "tests"
Requires-Dist: pytest==8.3.5 ; extra == "tests"
Requires-Dist: pytest-cov==6.1.1 ; extra == "tests"
Project-URL: Discussions, https://github.com/ansys/pyadditive/discussions
Project-URL: Documentation, https://additive.docs.pyansys.com
Project-URL: Issues, https://github.com/ansys/pyadditive/issues
Project-URL: Releases, https://github.com/ansys/pyadditive/releases
Project-URL: Source, https://github.com/ansys/pyadditive
Provides-Extra: doc
Provides-Extra: tests
